tf_plot_metrics/__init__.py
tf_plot_metrics-1.0.1.dist-info/METADATA
tf_plot_metrics-1.0.1.dist-info/WHEEL
tf_plot_metrics-1.0.1.dist-info/top_level.txt
tf_plot_metrics-1.0.1.dist-info/RECORD
